quant_candles/__init__.py
quant_candles/apps.py
quant_candles/constants.py
quant_candles/controllers/__init__.py
quant_candles/controllers/base.py
quant_candles/controllers/constants.py
quant_candles/controllers/iterators.py
quant_candles/controllers/rest.py
quant_candles/controllers/s3.py
quant_candles/exchanges/__init__.py
quant_candles/exchanges/alpaca/__init__.py
quant_candles/exchanges/api.py
quant_candles/exchanges/binance/__init__.py
quant_candles/exchanges/binance/api.py
quant_candles/exchanges/binance/base.py
quant_candles/exchanges/binance/candles.py
quant_candles/exchanges/binance/constants.py
quant_candles/exchanges/binance/controllers.py
quant_candles/exchanges/bitfinex/__init__.py
quant_candles/exchanges/bitfinex/api.py
quant_candles/exchanges/bitfinex/base.py
quant_candles/exchanges/bitfinex/candles.py
quant_candles/exchanges/bitfinex/constants.py
quant_candles/exchanges/bitfinex/controllers.py
quant_candles/exchanges/bitfinex/trades.py
quant_candles/exchanges/bitflyer/__init__.py
quant_candles/exchanges/bitflyer/api.py
quant_candles/exchanges/bitflyer/base.py
quant_candles/exchanges/bitflyer/constants.py
quant_candles/exchanges/bitflyer/controllers.py
quant_candles/exchanges/bitmex/__init__.py
quant_candles/exchanges/bitmex/api.py
quant_candles/exchanges/bitmex/base.py
quant_candles/exchanges/bitmex/candles.py
quant_candles/exchanges/bitmex/constants.py
quant_candles/exchanges/bitmex/controllers.py
quant_candles/exchanges/bitmex/funding.py
quant_candles/exchanges/bitmex/lib.py
quant_candles/exchanges/bitmex/trades.py
quant_candles/exchanges/bybit/__init__.py
quant_candles/exchanges/bybit/api.py
quant_candles/exchanges/bybit/base.py
quant_candles/exchanges/bybit/candles.py
quant_candles/exchanges/bybit/constants.py
quant_candles/exchanges/bybit/controllers.py
quant_candles/exchanges/coinbase/__init__.py
quant_candles/exchanges/coinbase/api.py
quant_candles/exchanges/coinbase/base.py
quant_candles/exchanges/coinbase/candles.py
django_quant_candles-0.1.2.dist-info/LICENSE
django_quant_candles-0.1.2.dist-info/WHEEL
django_quant_candles-0.1.2.dist-info/METADATA
django_quant_candles-0.1.2.dist-info/RECORD
